{
    "1.0.0": {
        "commit": "a1129fe4016b7b7f23b1d347b95448792ebe5d7b",
        "timestamp": "2021-07-11T02:57:37+0000",
        "files": 3
    },
    "1.0.1": {
        "commit": "e9cdcf3605108cada33edced72d82fc2f727861e",
        "timestamp": "2021-07-11T02:57:37+0000",
        "files": 3
    },
    "1.0.10": {
        "commit": "5913db6596d3f34156bb5014b83cfa4ebcabe127",
        "timestamp": "2021-07-11T02:57:39+0000",
        "files": 14
    },
    "1.0.11": {
        "commit": "c178711a8c3298a162f8b89e348a2b7ee1436218",
        "timestamp": "2021-07-11T02:57:39+0000",
        "files": 14
    },
    "1.0.12": {
        "commit": "3416cf39cf957ce4d9261bc65b6731343ec33842",
        "timestamp": "2021-07-11T02:57:40+0000",
        "files": 15
    },
    "1.0.13": {
        "commit": "a0c87d06cd5665bf0350d08db61e8f3ac13b7dea",
        "timestamp": "2021-07-11T02:57:40+0000",
        "files": 15
    },
    "1.0.15": {
        "commit": "1537bacbc038466095e83db8af84c1f6627e2b13",
        "timestamp": "2021-07-11T02:57:40+0000",
        "files": 15
    },
    "1.0.16": {
        "commit": "e061cdd5a46fe98e959c157e877c4c8c8d204129",
        "timestamp": "2021-07-11T02:57:40+0000",
        "files": 15
    },
    "1.0.17": {
        "commit": "459cfbf6665021df07e3e06495cf2ca35acee5b5",
        "timestamp": "2021-07-11T02:57:40+0000",
        "files": 15
    },
    "1.0.18": {
        "commit": "3860d42343a7ee0ee0fe40199b503c02de40c677",
        "timestamp": "2021-07-11T02:57:40+0000",
        "files": 15
    },
    "1.0.2": {
        "commit": "6c111e960dd282365746240067bf242bda5835f3",
        "timestamp": "2021-07-11T02:57:38+0000",
        "files": 6
    },
    "1.0.3": {
        "commit": "e1cd714ce9f210c1e08a915fc5ce3e5ac1713f00",
        "timestamp": "2021-07-11T02:57:38+0000",
        "files": 7
    },
    "1.0.4": {
        "commit": "babdb2633873227d2d562f180b561c5258d8bb42",
        "timestamp": "2021-07-11T02:57:38+0000",
        "files": 9
    },
    "1.0.5": {
        "commit": "e1f7ea08c4512d858a5c89e736e49fb88e41bdd2",
        "timestamp": "2021-07-11T02:57:38+0000",
        "files": 11
    },
    "1.0.6": {
        "commit": "8440a936343dcfa737339c905ba343bf9a884ab5",
        "timestamp": "2021-07-11T02:57:38+0000",
        "files": 11
    },
    "1.0.7": {
        "commit": "7cd3d87973ba8e36317daf7ecdd2e0196b5e23fc",
        "timestamp": "2021-07-11T02:57:39+0000",
        "files": 13
    },
    "1.0.8": {
        "commit": "0df99eb4eea59ee9b3d9f93f0435a1a3c8abc33b",
        "timestamp": "2021-07-11T02:57:39+0000",
        "files": 13
    },
    "1.0.9": {
        "commit": "1ba3815ab9efd6bc374a066a1e739f68a241f095",
        "timestamp": "2021-07-11T02:57:39+0000",
        "files": 14
    }
}