{
    "1.0.0": {
        "commit": "224e7a4339fcb775c7410c012ef12b4f452c0450",
        "timestamp": "2021-03-25T01:36:53+0000",
        "files": 3
    },
    "1.0.1": {
        "commit": "224666e3ecf6ec6c4ba349685f0abda8522a4350",
        "timestamp": "2021-03-25T01:36:53+0000",
        "files": 3
    },
    "1.0.10": {
        "commit": "7a482c206ef2fed58b7bac598eb0d6bebe271de6",
        "timestamp": "2021-03-25T01:36:55+0000",
        "files": 14
    },
    "1.0.11": {
        "commit": "0bfc8609766f770c9a496a27894bdb51d9428a50",
        "timestamp": "2021-03-25T01:36:56+0000",
        "files": 14
    },
    "1.0.12": {
        "commit": "b0cbc1fdf47f3012b9b1a552b49ff60f24942310",
        "timestamp": "2021-03-25T01:36:56+0000",
        "files": 15
    },
    "1.0.13": {
        "commit": "c15318d50092442e8b03f59319df57172c84e2c8",
        "timestamp": "2021-03-25T01:36:56+0000",
        "files": 15
    },
    "1.0.15": {
        "commit": "f444ba2fafe0eef932674beb9fe93849655d0153",
        "timestamp": "2021-03-25T01:36:56+0000",
        "files": 15
    },
    "1.0.2": {
        "commit": "ab43134de1afb382b37c0d90714222647ca7b895",
        "timestamp": "2021-03-25T01:36:53+0000",
        "files": 6
    },
    "1.0.3": {
        "commit": "a61ffee9b3e038d6f6155c09a1b656f8d54fd13e",
        "timestamp": "2021-03-25T01:36:54+0000",
        "files": 7
    },
    "1.0.4": {
        "commit": "1c657323d53f15a764c846eab40fcc5f8e4636bf",
        "timestamp": "2021-03-25T01:36:54+0000",
        "files": 9
    },
    "1.0.5": {
        "commit": "363dc2b61f13fe1ade681f7faa1e23fb50784843",
        "timestamp": "2021-03-25T01:36:54+0000",
        "files": 11
    },
    "1.0.6": {
        "commit": "40cef873bcf8d1ceb8f7c18bb8bad763afaf5dbd",
        "timestamp": "2021-03-25T01:36:54+0000",
        "files": 11
    },
    "1.0.7": {
        "commit": "51880a86deb4f390a4269b253cc79f31f02cdad2",
        "timestamp": "2021-03-25T01:36:55+0000",
        "files": 13
    },
    "1.0.8": {
        "commit": "38cc932817c2f5d2c3dfd4d51ae18ca77cbcd37f",
        "timestamp": "2021-03-25T01:36:55+0000",
        "files": 13
    },
    "1.0.9": {
        "commit": "5fe66d7e80e85e3643d5c0a1a1e3d1d1a8a8125c",
        "timestamp": "2021-03-25T01:36:55+0000",
        "files": 14
    }
}