{
    "v0.10.0": {
        "commit": "d7e3bc8e5eec7cdfb83e9f4e3fe08b999b116761",
        "timestamp": "2021-05-13T02:49:34+0000",
        "files": 1744
    },
    "v0.11.0": {
        "commit": "02eb592be942399f30768302f999c5ab2fb4ec84",
        "timestamp": "2021-05-13T02:49:37+0000",
        "files": 3226
    },
    "v0.11.1": {
        "commit": "aad6a868e6a59e344f075e7e0863d27cf9bea260",
        "timestamp": "2021-05-13T02:49:40+0000",
        "files": 3223
    },
    "v0.11.2": {
        "commit": "85e3ed04d6b718ba7ba5b3765bb4bfb0ed8c4f8e",
        "timestamp": "2021-05-13T02:49:43+0000",
        "files": 3511
    },
    "v0.12.0": {
        "commit": "863e009f550c005a8d64f064b830697aea731bed",
        "timestamp": "2021-05-13T02:49:47+0000",
        "files": 4210
    },
    "v0.12.1": {
        "commit": "62b2c00ce87c22f7f80bd4a57563b0649ae1854b",
        "timestamp": "2021-05-13T02:49:50+0000",
        "files": 4210
    },
    "v0.13.0": {
        "commit": "c9472c47da460d442340553dfe68873b18adbe88",
        "timestamp": "2021-05-13T02:49:54+0000",
        "files": 5172
    },
    "v0.13.1": {
        "commit": "922ed29038856dfc94fa03cf76ad39b112385fe6",
        "timestamp": "2021-05-13T02:49:58+0000",
        "files": 5173
    },
    "v0.13.2": {
        "commit": "1fa0c64c4f6f38447d0fbc2d79ff9db88c442088",
        "timestamp": "2021-05-13T02:50:01+0000",
        "files": 5173
    },
    "v0.13.3": {
        "commit": "1e1ae97fcdd7ce736f17f8d1d0919733b78b1b8e",
        "timestamp": "2021-05-13T02:50:05+0000",
        "files": 5173
    },
    "v0.13.4": {
        "commit": "f077e874fd3f9b29c57511a97733e2cf73813bf4",
        "timestamp": "2021-05-13T02:50:08+0000",
        "files": 5173
    },
    "v0.14.0": {
        "commit": "eda827655f6cfae09b80aab103b731d2bdd8a69e",
        "timestamp": "2021-05-13T02:50:12+0000",
        "files": 5658
    },
    "v0.14.1": {
        "commit": "1f9e16929b6f1b4b8dca098878c8e30122e23a18",
        "timestamp": "2021-05-13T02:50:16+0000",
        "files": 5657
    },
    "v0.14.2": {
        "commit": "80b31167c57de7aa1c28029bcac0d8a410d9a465",
        "timestamp": "2021-05-13T02:50:20+0000",
        "files": 5659
    },
    "v0.15.0": {
        "commit": "7933c69fa06315df3eba6a2883095dd1a9c1eefd",
        "timestamp": "2021-05-13T02:50:24+0000",
        "files": 6277
    },
    "v0.15.1": {
        "commit": "a8e77223b493a132304ab978fbda80e6b5d1f1d7",
        "timestamp": "2021-05-13T02:50:28+0000",
        "files": 6278
    },
    "v0.15.2": {
        "commit": "e07ab79355c6f1080978d30b9059a50b555eec4b",
        "timestamp": "2021-05-13T02:50:32+0000",
        "files": 6281
    },
    "v0.15.3": {
        "commit": "0a09329269ae6d3f99fe63f2a344b12bc208eef3",
        "timestamp": "2021-05-13T02:50:36+0000",
        "files": 6282
    },
    "v0.15.4": {
        "commit": "499e321df4948350b1749651186704ae7314b043",
        "timestamp": "2021-05-13T02:50:40+0000",
        "files": 6289
    },
    "v0.16.0": {
        "commit": "31b632d6cbe01a6ca06a305852b143e34d9df960",
        "timestamp": "2021-05-13T02:50:44+0000",
        "files": 7331
    },
    "v0.8": {
        "commit": "9e1e1ab9633ac449b7a89168ecae59b3be5a355f",
        "timestamp": "2021-05-13T02:49:21+0000",
        "files": 192
    },
    "v0.8.10": {
        "commit": "b69ef6ab89f43e9df0c3793ed4e69a2b8dec3136",
        "timestamp": "2021-05-13T02:49:24+0000",
        "files": 262
    },
    "v0.8.11": {
        "commit": "cc5d91e164a7d73d4c196cafd5f31a7a3bac9e22",
        "timestamp": "2021-05-13T02:49:25+0000",
        "files": 262
    },
    "v0.8.15": {
        "commit": "f5ec18a568169016e4822ed0135848e745415840",
        "timestamp": "2021-05-13T02:49:26+0000",
        "files": 377
    },
    "v0.8.16": {
        "commit": "2f61f1db8faa0bbc6e6f205c50967bf86b67eb65",
        "timestamp": "2021-05-13T02:49:27+0000",
        "files": 378
    },
    "v0.8.17": {
        "commit": "b67fb6e1bd0bfaf1b800b711099e4a83bc865b76",
        "timestamp": "2021-05-13T02:49:29+0000",
        "files": 378
    },
    "v0.8.5": {
        "commit": "29a5f0c521992ee33b6f8bcc8c19080f61311001",
        "timestamp": "2021-05-13T02:49:23+0000",
        "files": 233
    },
    "v0.9": {
        "commit": "756b63a49c17955cde0a2956dc097eb20a51e708",
        "timestamp": "2021-05-13T02:49:30+0000",
        "files": 847
    },
    "v0.9.1": {
        "commit": "796ff8f16f3e3a556c91c72de96437762392dc04",
        "timestamp": "2021-05-13T02:49:32+0000",
        "files": 847
    }
}