{
    "v0.10.0": {
        "commit": "9e9269c6aa35b366fe83e6d54dde041d76a20cce",
        "timestamp": "2021-05-15T04:14:23+0000",
        "files": 1744
    },
    "v0.11.0": {
        "commit": "70ac9ed2c14f6f1c99d52138edecbc1d3e04e9e0",
        "timestamp": "2021-05-15T04:14:26+0000",
        "files": 3226
    },
    "v0.11.1": {
        "commit": "3a9a0cbf66ac3031eca28c5dc4dfc116f1222ce9",
        "timestamp": "2021-05-15T04:14:28+0000",
        "files": 3223
    },
    "v0.11.2": {
        "commit": "27fe2364fac505d0a5d5c1691eef933a94f23f53",
        "timestamp": "2021-05-15T04:14:31+0000",
        "files": 3511
    },
    "v0.12.0": {
        "commit": "800448d9562c4dcd00e2c3162c3d8d6d62c0f2e0",
        "timestamp": "2021-05-15T04:14:35+0000",
        "files": 4210
    },
    "v0.12.1": {
        "commit": "caf0d22c513e4319d0da136e2269e31f0ab04c50",
        "timestamp": "2021-05-15T04:14:39+0000",
        "files": 4210
    },
    "v0.13.0": {
        "commit": "e8ed80f2b8bce0af0c014a92e8833ae39503aa90",
        "timestamp": "2021-05-15T04:14:43+0000",
        "files": 5172
    },
    "v0.13.1": {
        "commit": "111a5fadf299f2ca1d04be878bda55663ff22926",
        "timestamp": "2021-05-15T04:14:47+0000",
        "files": 5173
    },
    "v0.13.2": {
        "commit": "bcd288c361a884626889acee9d5724a5fe40024c",
        "timestamp": "2021-05-15T04:14:49+0000",
        "files": 5173
    },
    "v0.13.3": {
        "commit": "f9adc4d5a2eb6c0f3aa12b64ce5e45ba59a22b10",
        "timestamp": "2021-05-15T04:14:52+0000",
        "files": 5173
    },
    "v0.13.4": {
        "commit": "1a86656aab614a86017213d9fe6da0b1afe0e5a4",
        "timestamp": "2021-05-15T04:14:54+0000",
        "files": 5173
    },
    "v0.14.0": {
        "commit": "e565b15ea7dd57a32e71eaaa4f54c53ec5b1fa73",
        "timestamp": "2021-05-15T04:14:58+0000",
        "files": 5658
    },
    "v0.14.1": {
        "commit": "c7d851adf0f6db2a8b0572d016cedbfcda4681ec",
        "timestamp": "2021-05-15T04:15:02+0000",
        "files": 5657
    },
    "v0.14.2": {
        "commit": "78f9840de3a838e53c7e6dfe9102385b2bc8884e",
        "timestamp": "2021-05-15T04:15:04+0000",
        "files": 5659
    },
    "v0.15.0": {
        "commit": "7bf6590e3c0a1c1cdffb83c48ac09c46342a202b",
        "timestamp": "2021-05-15T04:15:08+0000",
        "files": 6277
    },
    "v0.15.1": {
        "commit": "ae10800d9c255f93072f6b745a32ce35f7ae27db",
        "timestamp": "2021-05-15T04:15:11+0000",
        "files": 6278
    },
    "v0.15.2": {
        "commit": "238eff7116d102a743d8a0c402b8c0b49e71d8ad",
        "timestamp": "2021-05-15T04:15:14+0000",
        "files": 6281
    },
    "v0.15.3": {
        "commit": "a21c1f10573a3bd4ed7d532e0a25a274c6861c9f",
        "timestamp": "2021-05-15T04:15:17+0000",
        "files": 6282
    },
    "v0.15.4": {
        "commit": "ed4dbfa3e22e233909965764e8c5af624b56eb78",
        "timestamp": "2021-05-15T04:15:21+0000",
        "files": 6289
    },
    "v0.16.0": {
        "commit": "6f84e7cfd83199fab046be1ffd8cf3603c9acecb",
        "timestamp": "2021-05-15T04:15:25+0000",
        "files": 7331
    },
    "v0.8": {
        "commit": "ca175e8c8cf24632bf0a48c779c8d7d5474a7592",
        "timestamp": "2021-05-15T04:14:16+0000",
        "files": 192
    },
    "v0.8.10": {
        "commit": "7fb7cca7f43188cad9be21dc74eb7f66b3d8d7e6",
        "timestamp": "2021-05-15T04:14:17+0000",
        "files": 262
    },
    "v0.8.11": {
        "commit": "a385aadaf25023c10688b9ea74d0d3696091765b",
        "timestamp": "2021-05-15T04:14:18+0000",
        "files": 262
    },
    "v0.8.15": {
        "commit": "2a4d56f5135f4c83a2c929028048189f2f9ca28b",
        "timestamp": "2021-05-15T04:14:18+0000",
        "files": 377
    },
    "v0.8.16": {
        "commit": "1f1bb23ddee5c373719cde532e2d47e7e5b51d3b",
        "timestamp": "2021-05-15T04:14:19+0000",
        "files": 378
    },
    "v0.8.17": {
        "commit": "0bf0c4a57195ed94153c3f1e4d37acded4182895",
        "timestamp": "2021-05-15T04:14:19+0000",
        "files": 378
    },
    "v0.8.5": {
        "commit": "966ca8f1f79598f2af8e602b9f1a5cab5cfe40e5",
        "timestamp": "2021-05-15T04:14:17+0000",
        "files": 233
    },
    "v0.9": {
        "commit": "2c14c4bddf3a8948b5f29defd0ef58e66176882b",
        "timestamp": "2021-05-15T04:14:20+0000",
        "files": 847
    },
    "v0.9.1": {
        "commit": "207927b3b0329d530e08ef5461982a047aa5d225",
        "timestamp": "2021-05-15T04:14:21+0000",
        "files": 847
    }
}