{
    "1.10.0": {
        "commit": "f037bd6d1c94b37ee337517f0878ecd151abc25a",
        "timestamp": "2021-07-10T06:15:24+0000",
        "files": 1225
    },
    "1.10.1": {
        "commit": "72dd417e20aa163f3b73170ec90d6bb570ef2d42",
        "timestamp": "2021-07-10T06:15:25+0000",
        "files": 1226
    },
    "1.10.2": {
        "commit": "3f08fb32e36b9333d1d74dcd708983e3c2ad1255",
        "timestamp": "2021-07-10T06:15:27+0000",
        "files": 1227
    },
    "1.10.3": {
        "commit": "fe30a601145fa68493d3139b64cd9a9bde750d34",
        "timestamp": "2021-07-10T06:15:30+0000",
        "files": 1254
    },
    "1.10.4": {
        "commit": "41fc919d8b143761b9d6100e62ca359f89158630",
        "timestamp": "2021-07-10T06:15:31+0000",
        "files": 1230
    },
    "1.11.0": {
        "commit": "a80bac6f9081e6a66ae24cb9f68f5d11b048804c",
        "timestamp": "2021-07-10T06:15:32+0000",
        "files": 1210
    },
    "1.11.1": {
        "commit": "242d1b45a3da969e2159c9f2df16c26f6c9ba600",
        "timestamp": "2021-07-10T06:15:34+0000",
        "files": 1211
    },
    "1.11.2": {
        "commit": "9e48d982ee3521868120d6d32f283755ad2faaa4",
        "timestamp": "2021-07-10T06:15:35+0000",
        "files": 1214
    },
    "1.11.3": {
        "commit": "84a50b2ee8c40adb0d785fbe5d4ab10174ae004f",
        "timestamp": "2021-07-10T06:15:38+0000",
        "files": 1240
    },
    "1.12.0": {
        "commit": "9d0a0f6b00af5afd65e8f737b2b37f401266dd56",
        "timestamp": "2021-07-10T06:15:39+0000",
        "files": 1262
    },
    "1.12.1": {
        "commit": "808967a968abe2a72dc88c6d52ce4e5dc7338f01",
        "timestamp": "2021-07-10T06:15:41+0000",
        "files": 1264
    },
    "1.13.0": {
        "commit": "95e90b419d0719a9631b426ace54bfa7241e7a73",
        "timestamp": "2021-07-10T06:15:42+0000",
        "files": 1269
    },
    "1.13.0rc1": {
        "commit": "da0cdf8d23ab05741d58fb129a930a30889282aa",
        "timestamp": "2021-07-10T06:15:43+0000",
        "files": 1269
    },
    "1.13.0rc2": {
        "commit": "aa058e1402a054ae20002884f31ed3cdfffd3061",
        "timestamp": "2021-07-10T06:15:45+0000",
        "files": 1269
    },
    "1.13.1": {
        "commit": "dadd9f7fa9c7f45a9e7908fe98e332303b52b023",
        "timestamp": "2021-07-10T06:15:46+0000",
        "files": 1271
    },
    "1.13.3": {
        "commit": "6fbc3b76790381a190330781b58975e99a15e9f6",
        "timestamp": "2021-07-10T06:15:49+0000",
        "files": 1272
    },
    "1.14.0": {
        "commit": "66c660f51b41fce515f6425c97c6cb1d29052a22",
        "timestamp": "2021-07-10T06:15:51+0000",
        "files": 1296
    },
    "1.14.0rc1": {
        "commit": "4abc9d78497dcbb1d6f3fb9c66ff22f6a46a927d",
        "timestamp": "2021-07-10T06:15:53+0000",
        "files": 1297
    },
    "1.14.1": {
        "commit": "387775983fc2e922741b322fb22cd1d5a389bcc7",
        "timestamp": "2021-07-10T06:15:55+0000",
        "files": 1297
    },
    "1.14.2": {
        "commit": "3cd5f96567f1f7acd78bc0e028747aced4398a75",
        "timestamp": "2021-07-10T06:15:58+0000",
        "files": 1297
    },
    "1.14.3": {
        "commit": "a54c0845a7dd1b7227da7aff0d473b1148d40020",
        "timestamp": "2021-07-10T06:16:01+0000",
        "files": 1297
    },
    "1.14.4": {
        "commit": "8caa3458703b1540c2a9955197ca5ad74f13615e",
        "timestamp": "2021-07-10T06:16:03+0000",
        "files": 1297
    },
    "1.14.5": {
        "commit": "5b101e4d197dd7d861abe9f7bd8e77235295cb2b",
        "timestamp": "2021-07-10T06:16:06+0000",
        "files": 1309
    },
    "1.14.6": {
        "commit": "219c9816b025791360b44deb8d1b7336dc91a753",
        "timestamp": "2021-07-10T06:16:09+0000",
        "files": 1310
    },
    "1.15.0": {
        "commit": "3796b69fdd60bf123c7df054bce6a52c0826a14d",
        "timestamp": "2021-07-10T06:16:11+0000",
        "files": 1334
    },
    "1.15.0rc1": {
        "commit": "6b3ee0e8d5d9e83b2c788872922a48906dfc9d7f",
        "timestamp": "2021-07-10T06:16:14+0000",
        "files": 1339
    },
    "1.15.0rc2": {
        "commit": "c4e516d7d5adb9d738d8611bd8e8796c7e2558f5",
        "timestamp": "2021-07-10T06:16:17+0000",
        "files": 1339
    },
    "1.15.1": {
        "commit": "e39422fd338c26e1dbb0577c4ac361d80024eb43",
        "timestamp": "2021-07-10T06:16:20+0000",
        "files": 1339
    },
    "1.15.2": {
        "commit": "f7535f719e4f167727131a6e91bd4018121866e7",
        "timestamp": "2021-07-10T06:16:23+0000",
        "files": 1339
    },
    "1.15.3": {
        "commit": "cdd62bc85980396ce12765397edb2dde259757f7",
        "timestamp": "2021-07-10T06:16:26+0000",
        "files": 1339
    },
    "1.15.4": {
        "commit": "b2ded61f7ba5600a9d37045d75474478d50f3dfc",
        "timestamp": "2021-07-10T06:16:29+0000",
        "files": 1339
    },
    "1.16.0": {
        "commit": "bcc9eac0ac5b26e9cdd99fe901e0a78285d6a9d8",
        "timestamp": "2021-07-10T06:16:31+0000",
        "files": 1357
    },
    "1.16.0rc1": {
        "commit": "01cc807629894c5bb9d202db5426e7d9f28e9748",
        "timestamp": "2021-07-10T06:16:33+0000",
        "files": 1357
    },
    "1.16.0rc2": {
        "commit": "fd447a482869161d1ea5a7200ed37192c625ccb0",
        "timestamp": "2021-07-10T06:16:36+0000",
        "files": 1357
    },
    "1.16.1": {
        "commit": "1423b1cdf5bfc10e75330596b570dccfb92a3c42",
        "timestamp": "2021-07-10T06:16:38+0000",
        "files": 1358
    },
    "1.16.2": {
        "commit": "e1e78b8443c6f8a722b9bb56878eb936e358220a",
        "timestamp": "2021-07-10T06:16:41+0000",
        "files": 1360
    },
    "1.16.3": {
        "commit": "9b51e4183086f874159502a1532acbb488ef273f",
        "timestamp": "2021-07-10T06:16:43+0000",
        "files": 1360
    },
    "1.16.4": {
        "commit": "40f42b00258151916b7af985e91e5b77a8dae467",
        "timestamp": "2021-07-10T06:16:46+0000",
        "files": 1361
    },
    "1.16.5": {
        "commit": "ca49dadb1935ecf1343b646a80ab3c9fb1ca6a82",
        "timestamp": "2021-07-10T06:16:48+0000",
        "files": 1362
    },
    "1.16.6": {
        "commit": "e5f6781e6f6605df276b0083e80626333e3681d1",
        "timestamp": "2021-07-10T06:16:50+0000",
        "files": 1362
    },
    "1.17.0": {
        "commit": "46f8fb27d19824f350fc3807836cd6f4ec4843df",
        "timestamp": "2021-07-10T06:16:53+0000",
        "files": 1404
    },
    "1.17.0rc1": {
        "commit": "45fdb2822decded0c8b357232cbc47445f8557e4",
        "timestamp": "2021-07-10T06:16:56+0000",
        "files": 1404
    },
    "1.17.0rc2": {
        "commit": "0e704c04cc44da1b34a6fe33f50175a9fce13181",
        "timestamp": "2021-07-10T06:16:59+0000",
        "files": 1404
    },
    "1.17.1": {
        "commit": "a2604895ceeb479bf5698c05238211b2aafc96b9",
        "timestamp": "2021-07-10T06:17:01+0000",
        "files": 1404
    },
    "1.17.2": {
        "commit": "783a74d9815faebde790ef8254f69ccd5abbd11a",
        "timestamp": "2021-07-10T06:17:04+0000",
        "files": 1404
    },
    "1.17.3": {
        "commit": "30050838182d8011395928e37595dce916196819",
        "timestamp": "2021-07-10T06:17:06+0000",
        "files": 1425
    },
    "1.17.4": {
        "commit": "f87ede889a38e729a44bd50e28ec5ae3e8b614f7",
        "timestamp": "2021-07-10T06:17:08+0000",
        "files": 1425
    },
    "1.17.5": {
        "commit": "b14a784737fe8068254ee37ed6d22f4bfe372771",
        "timestamp": "2021-07-10T06:17:11+0000",
        "files": 1425
    },
    "1.18.0": {
        "commit": "d0573ae2fc63c09f0a97b367785820a88a365503",
        "timestamp": "2021-07-10T06:17:14+0000",
        "files": 1448
    },
    "1.18.0rc1": {
        "commit": "890bb68fc351666b23d4afd0e7ca22a245f95354",
        "timestamp": "2021-07-10T06:17:17+0000",
        "files": 1448
    },
    "1.18.1": {
        "commit": "b03ee23eb04365286a21fb9b875fca1038eb6ead",
        "timestamp": "2021-07-10T06:17:19+0000",
        "files": 1448
    },
    "1.18.2": {
        "commit": "7f797ad4b4bd5a29999f9b377371e42592b8d814",
        "timestamp": "2021-07-10T06:17:21+0000",
        "files": 1449
    },
    "1.18.3": {
        "commit": "0b0882568a58544c6a8b44787f66f593317b4d62",
        "timestamp": "2021-07-10T06:17:24+0000",
        "files": 1449
    },
    "1.18.4": {
        "commit": "b51fc78772f1a42d5f4e1d33871b558539d10f85",
        "timestamp": "2021-07-10T06:17:26+0000",
        "files": 1449
    },
    "1.18.5": {
        "commit": "85db08ed4d2fe5222b76039d06653d79bb03b29c",
        "timestamp": "2021-07-10T06:17:29+0000",
        "files": 1449
    },
    "1.19.0": {
        "commit": "cbd36ce7de73e5914a7c3d2f2e0d76f9bc4a999c",
        "timestamp": "2021-07-10T06:17:31+0000",
        "files": 1478
    },
    "1.19.0rc1": {
        "commit": "00259f14d9568d8e3776f3a3908e729276123e44",
        "timestamp": "2021-07-10T06:17:33+0000",
        "files": 1478
    },
    "1.19.0rc2": {
        "commit": "fad22172fe904e8cda64ba1ab48d41993bc6dbdf",
        "timestamp": "2021-07-10T06:17:34+0000",
        "files": 1478
    },
    "1.19.1": {
        "commit": "e90511be0165c2e71d2345baed7dbffeb349aa3d",
        "timestamp": "2021-07-10T06:17:36+0000",
        "files": 1478
    },
    "1.19.2": {
        "commit": "f3e4b1a8b4e2e020894fe89b65577048c560e015",
        "timestamp": "2021-07-10T06:17:37+0000",
        "files": 1479
    },
    "1.19.3": {
        "commit": "0181fdb1ff598b3b762c3875ddd56abde878d958",
        "timestamp": "2021-07-10T06:17:39+0000",
        "files": 1481
    },
    "1.19.4": {
        "commit": "743b827aaca673b7929953ac939bead398587348",
        "timestamp": "2021-07-10T06:17:41+0000",
        "files": 1481
    },
    "1.19.5": {
        "commit": "1e0e5eb9cc182d23f6b945eb4f507aa6a1ebc0dd",
        "timestamp": "2021-07-10T06:17:43+0000",
        "files": 1482
    },
    "1.20.0rc1": {
        "commit": "c8ffaea1c49fad0d6c37569eace8ba89e03b8187",
        "timestamp": "2021-07-10T06:17:45+0000",
        "files": 1643
    },
    "1.20.0rc2": {
        "commit": "fddcae347beb315c65a640198beacdd26fcd5f43",
        "timestamp": "2021-07-10T06:17:46+0000",
        "files": 1644
    },
    "1.20.2": {
        "commit": "59b9abe4efffbbd45ece193bc55e02163402585c",
        "timestamp": "2021-07-10T06:17:48+0000",
        "files": 1648
    },
    "1.21.0rc2": {
        "commit": "ef7822ffbb8e67981f14022f04af58d02ebc08c4",
        "timestamp": "2021-07-10T06:17:51+0000",
        "files": 1741
    },
    "1.3.0": {
        "commit": "06264c5b788d5a902cf647efc747eaf25ae168ea",
        "timestamp": "2021-07-10T06:17:52+0000",
        "files": 1528
    },
    "1.4.1": {
        "commit": "1f597f3adf75632325613bcbeaa7928189050c45",
        "timestamp": "2021-07-10T06:17:55+0000",
        "files": 723
    },
    "1.5.0": {
        "commit": "c8d7c922671a1247e1d77e83529831b53c54ab58",
        "timestamp": "2021-07-10T06:17:56+0000",
        "files": 697
    },
    "1.5.1": {
        "commit": "b9e79c6c72a5174b1845442e8a6fe82b6095394f",
        "timestamp": "2021-07-10T06:17:57+0000",
        "files": 698
    },
    "1.6.0": {
        "commit": "f60485b88effc5e6f424620a8874cb216cff1b9a",
        "timestamp": "2021-07-10T06:17:58+0000",
        "files": 2643
    },
    "1.6.1": {
        "commit": "5c54694972898aab344a8e24a8d352ea10d8de5c",
        "timestamp": "2021-07-10T06:18:00+0000",
        "files": 2741
    },
    "1.6.2": {
        "commit": "cbd583f1769a954c2dc752ad68d65fadf9e892d5",
        "timestamp": "2021-07-10T06:18:01+0000",
        "files": 822
    },
    "1.7.0": {
        "commit": "6729b87bc8f6a400c7325847b373517c2e23e08f",
        "timestamp": "2021-07-10T06:18:03+0000",
        "files": 860
    },
    "1.7.1": {
        "commit": "aa9167d17e078f9e5b09a9514ee4b43b9e9af715",
        "timestamp": "2021-07-10T06:18:04+0000",
        "files": 863
    },
    "1.7.2": {
        "commit": "1be884cb0ca842acf5d63f6434040cbecfd0f9a6",
        "timestamp": "2021-07-10T06:18:05+0000",
        "files": 866
    },
    "1.8.0": {
        "commit": "9be51d8ec9ef08f36754ad3567fde86cb36d0a5b",
        "timestamp": "2021-07-10T06:18:07+0000",
        "files": 1181
    },
    "1.8.1": {
        "commit": "f969c4b57934507f8af3009dcc3aa2ec5c891022",
        "timestamp": "2021-07-10T06:18:09+0000",
        "files": 1202
    },
    "1.8.2": {
        "commit": "992c0e08278a17e04760e5d6e0ed34645b22daa6",
        "timestamp": "2021-07-10T06:18:10+0000",
        "files": 1203
    },
    "1.9.0": {
        "commit": "0aad820745c5287fedb6adf66c9ce4825b036b67",
        "timestamp": "2021-07-10T06:18:11+0000",
        "files": 1211
    },
    "1.9.1": {
        "commit": "4a0a3832e8d02fa52c12c020552bcf3db158dbd3",
        "timestamp": "2021-07-10T06:18:13+0000",
        "files": 1219
    },
    "1.9.2": {
        "commit": "2e98e7ce24534eb591fbbf20c064ae348d69113d",
        "timestamp": "2021-07-10T06:18:14+0000",
        "files": 1221
    },
    "1.9.3": {
        "commit": "baf7851bc0fc3a810780138d0cd18d9dd80c698e",
        "timestamp": "2021-07-10T06:18:15+0000",
        "files": 1220
    }
}