{
    "EMPTY..0.0.1": {
        "by-file": [
            {
                "insertions": 661,
                "deletions": 0,
                "lines": 661,
                "object": "/tmp/sif-uqcnahpz/LICENSE",
                "commit": "1882950f08bef6e09a77d1be7e740288c1ec5d5f",
                "author": "vsoch-caliper@users.noreply.github.com",
                "timestamp": "2021-01-17T14:07:01-0700"
            },
            {
                "insertions": 9,
                "deletions": 0,
                "lines": 9,
                "object": "/tmp/sif-uqcnahpz/MANIFEST.in",
                "commit": "1882950f08bef6e09a77d1be7e740288c1ec5d5f",
                "author": "vsoch-caliper@users.noreply.github.com",
                "timestamp": "2021-01-17T14:07:01-0700"
            },
            {
                "insertions": 28,
                "deletions": 0,
                "lines": 28,
                "object": "/tmp/sif-uqcnahpz/PKG-INFO",
                "commit": "1882950f08bef6e09a77d1be7e740288c1ec5d5f",
                "author": "vsoch-caliper@users.noreply.github.com",
                "timestamp": "2021-01-17T14:07:01-0700"
            },
            {
                "insertions": 8,
                "deletions": 0,
                "lines": 8,
                "object": "/tmp/sif-uqcnahpz/README.md",
                "commit": "1882950f08bef6e09a77d1be7e740288c1ec5d5f",
                "author": "vsoch-caliper@users.noreply.github.com",
                "timestamp": "2021-01-17T14:07:01-0700"
            },
            {
                "insertions": 4,
                "deletions": 0,
                "lines": 4,
                "object": "/tmp/sif-uqcnahpz/setup.cfg",
                "commit": "1882950f08bef6e09a77d1be7e740288c1ec5d5f",
                "author": "vsoch-caliper@users.noreply.github.com",
                "timestamp": "2021-01-17T14:07:01-0700"
            },
            {
                "insertions": 118,
                "deletions": 0,
                "lines": 118,
                "object": "/tmp/sif-uqcnahpz/setup.py",
                "commit": "1882950f08bef6e09a77d1be7e740288c1ec5d5f",
                "author": "vsoch-caliper@users.noreply.github.com",
                "timestamp": "2021-01-17T14:07:01-0700"
            },
            {
                "insertions": 28,
                "deletions": 0,
                "lines": 28,
                "object": "/tmp/sif-uqcnahpz/sif.egg-info/PKG-INFO",
                "commit": "1882950f08bef6e09a77d1be7e740288c1ec5d5f",
                "author": "vsoch-caliper@users.noreply.github.com",
                "timestamp": "2021-01-17T14:07:01-0700"
            },
            {
                "insertions": 12,
                "deletions": 0,
                "lines": 12,
                "object": "/tmp/sif-uqcnahpz/sif.egg-info/SOURCES.txt",
                "commit": "1882950f08bef6e09a77d1be7e740288c1ec5d5f",
                "author": "vsoch-caliper@users.noreply.github.com",
                "timestamp": "2021-01-17T14:07:01-0700"
            },
            {
                "insertions": 1,
                "deletions": 0,
                "lines": 1,
                "object": "/tmp/sif-uqcnahpz/sif.egg-info/dependency_links.txt",
                "commit": "1882950f08bef6e09a77d1be7e740288c1ec5d5f",
                "author": "vsoch-caliper@users.noreply.github.com",
                "timestamp": "2021-01-17T14:07:01-0700"
            },
            {
                "insertions": 3,
                "deletions": 0,
                "lines": 3,
                "object": "/tmp/sif-uqcnahpz/sif.egg-info/entry_points.txt",
                "commit": "1882950f08bef6e09a77d1be7e740288c1ec5d5f",
                "author": "vsoch-caliper@users.noreply.github.com",
                "timestamp": "2021-01-17T14:07:01-0700"
            },
            {
                "insertions": 1,
                "deletions": 0,
                "lines": 1,
                "object": "/tmp/sif-uqcnahpz/sif.egg-info/not-zip-safe",
                "commit": "1882950f08bef6e09a77d1be7e740288c1ec5d5f",
                "author": "vsoch-caliper@users.noreply.github.com",
                "timestamp": "2021-01-17T14:07:01-0700"
            },
            {
                "insertions": 1,
                "deletions": 0,
                "lines": 1,
                "object": "/tmp/sif-uqcnahpz/sif.egg-info/top_level.txt",
                "commit": "1882950f08bef6e09a77d1be7e740288c1ec5d5f",
                "author": "vsoch-caliper@users.noreply.github.com",
                "timestamp": "2021-01-17T14:07:01-0700"
            },
            {
                "insertions": 20,
                "deletions": 0,
                "lines": 20,
                "object": "/tmp/sif-uqcnahpz/sif/__init__.py",
                "commit": "1882950f08bef6e09a77d1be7e740288c1ec5d5f",
                "author": "vsoch-caliper@users.noreply.github.com",
                "timestamp": "2021-01-17T14:07:01-0700"
            },
            {
                "insertions": 29,
                "deletions": 0,
                "lines": 29,
                "object": "/tmp/sif-uqcnahpz/sif/version.py",
                "commit": "1882950f08bef6e09a77d1be7e740288c1ec5d5f",
                "author": "vsoch-caliper@users.noreply.github.com",
                "timestamp": "2021-01-17T14:07:01-0700"
            }
        ],
        "by-group": {
            "insertions": 923,
            "deletions": 0,
            "lines": 923
        }
    },
    "0.0.1..0.0.11": {
        "by-file": [
            {
                "insertions": 151,
                "deletions": 5,
                "lines": 156,
                "object": "/tmp/sif-uqcnahpz/PKG-INFO",
                "commit": "99fd2482cf88dfcfd157ff9fc4f1db79605e4189",
                "author": "vsoch-caliper@users.noreply.github.com",
                "timestamp": "2021-01-17T14:07:01-0700"
            },
            {
                "insertions": 147,
                "deletions": 2,
                "lines": 149,
                "object": "/tmp/sif-uqcnahpz/README.md",
                "commit": "99fd2482cf88dfcfd157ff9fc4f1db79605e4189",
                "author": "vsoch-caliper@users.noreply.github.com",
                "timestamp": "2021-01-17T14:07:01-0700"
            },
            {
                "insertions": 2,
                "deletions": 2,
                "lines": 4,
                "object": "/tmp/sif-uqcnahpz/setup.py",
                "commit": "99fd2482cf88dfcfd157ff9fc4f1db79605e4189",
                "author": "vsoch-caliper@users.noreply.github.com",
                "timestamp": "2021-01-17T14:07:01-0700"
            },
            {
                "insertions": 151,
                "deletions": 5,
                "lines": 156,
                "object": "/tmp/sif-uqcnahpz/sif.egg-info/PKG-INFO",
                "commit": "99fd2482cf88dfcfd157ff9fc4f1db79605e4189",
                "author": "vsoch-caliper@users.noreply.github.com",
                "timestamp": "2021-01-17T14:07:01-0700"
            },
            {
                "insertions": 21,
                "deletions": 1,
                "lines": 22,
                "object": "/tmp/sif-uqcnahpz/sif.egg-info/SOURCES.txt",
                "commit": "99fd2482cf88dfcfd157ff9fc4f1db79605e4189",
                "author": "vsoch-caliper@users.noreply.github.com",
                "timestamp": "2021-01-17T14:07:01-0700"
            },
            {
                "insertions": 1,
                "deletions": 1,
                "lines": 2,
                "object": "/tmp/sif-uqcnahpz/sif.egg-info/entry_points.txt",
                "commit": "99fd2482cf88dfcfd157ff9fc4f1db79605e4189",
                "author": "vsoch-caliper@users.noreply.github.com",
                "timestamp": "2021-01-17T14:07:01-0700"
            },
            {
                "insertions": 1,
                "deletions": 0,
                "lines": 1,
                "object": "/tmp/sif-uqcnahpz/sif/__init__.py",
                "commit": "99fd2482cf88dfcfd157ff9fc4f1db79605e4189",
                "author": "vsoch-caliper@users.noreply.github.com",
                "timestamp": "2021-01-17T14:07:01-0700"
            },
            {
                "insertions": 134,
                "deletions": 0,
                "lines": 134,
                "object": "/tmp/sif-uqcnahpz/sif/client/__init__.py",
                "commit": "99fd2482cf88dfcfd157ff9fc4f1db79605e4189",
                "author": "vsoch-caliper@users.noreply.github.com",
                "timestamp": "2021-01-17T14:07:01-0700"
            },
            {
                "insertions": 71,
                "deletions": 0,
                "lines": 71,
                "object": "/tmp/sif-uqcnahpz/sif/client/shell.py",
                "commit": "99fd2482cf88dfcfd157ff9fc4f1db79605e4189",
                "author": "vsoch-caliper@users.noreply.github.com",
                "timestamp": "2021-01-17T14:07:01-0700"
            },
            {
                "insertions": 44,
                "deletions": 0,
                "lines": 44,
                "object": "/tmp/sif-uqcnahpz/sif/defaults.py",
                "commit": "99fd2482cf88dfcfd157ff9fc4f1db79605e4189",
                "author": "vsoch-caliper@users.noreply.github.com",
                "timestamp": "2021-01-17T14:07:01-0700"
            },
            {
                "insertions": 62,
                "deletions": 0,
                "lines": 62,
                "object": "/tmp/sif-uqcnahpz/sif/header/__init__.py",
                "commit": "99fd2482cf88dfcfd157ff9fc4f1db79605e4189",
                "author": "vsoch-caliper@users.noreply.github.com",
                "timestamp": "2021-01-17T14:07:01-0700"
            },
            {
                "insertions": 26,
                "deletions": 0,
                "lines": 26,
                "object": "/tmp/sif-uqcnahpz/sif/header/v02/__init__.py",
                "commit": "99fd2482cf88dfcfd157ff9fc4f1db79605e4189",
                "author": "vsoch-caliper@users.noreply.github.com",
                "timestamp": "2021-01-17T14:07:01-0700"
            },
            {
                "insertions": 109,
                "deletions": 0,
                "lines": 109,
                "object": "/tmp/sif-uqcnahpz/sif/header/v02/descriptors.py",
                "commit": "99fd2482cf88dfcfd157ff9fc4f1db79605e4189",
                "author": "vsoch-caliper@users.noreply.github.com",
                "timestamp": "2021-01-17T14:07:01-0700"
            },
            {
                "insertions": 111,
                "deletions": 0,
                "lines": 111,
                "object": "/tmp/sif-uqcnahpz/sif/header/v02/globalHeader.py",
                "commit": "99fd2482cf88dfcfd157ff9fc4f1db79605e4189",
                "author": "vsoch-caliper@users.noreply.github.com",
                "timestamp": "2021-01-17T14:07:01-0700"
            },
            {
                "insertions": 3,
                "deletions": 0,
                "lines": 3,
                "object": "/tmp/sif-uqcnahpz/sif/logger/__init__.py",
                "commit": "99fd2482cf88dfcfd157ff9fc4f1db79605e4189",
                "author": "vsoch-caliper@users.noreply.github.com",
                "timestamp": "2021-01-17T14:07:01-0700"
            },
            {
                "insertions": 356,
                "deletions": 0,
                "lines": 356,
                "object": "/tmp/sif-uqcnahpz/sif/logger/message.py",
                "commit": "99fd2482cf88dfcfd157ff9fc4f1db79605e4189",
                "author": "vsoch-caliper@users.noreply.github.com",
                "timestamp": "2021-01-17T14:07:01-0700"
            },
            {
                "insertions": 95,
                "deletions": 0,
                "lines": 95,
                "object": "/tmp/sif-uqcnahpz/sif/logger/namer.py",
                "commit": "99fd2482cf88dfcfd157ff9fc4f1db79605e4189",
                "author": "vsoch-caliper@users.noreply.github.com",
                "timestamp": "2021-01-17T14:07:01-0700"
            },
            {
                "insertions": 135,
                "deletions": 0,
                "lines": 135,
                "object": "/tmp/sif-uqcnahpz/sif/logger/progress.py",
                "commit": "99fd2482cf88dfcfd157ff9fc4f1db79605e4189",
                "author": "vsoch-caliper@users.noreply.github.com",
                "timestamp": "2021-01-17T14:07:01-0700"
            },
            {
                "insertions": 85,
                "deletions": 0,
                "lines": 85,
                "object": "/tmp/sif-uqcnahpz/sif/logger/spinner.py",
                "commit": "99fd2482cf88dfcfd157ff9fc4f1db79605e4189",
                "author": "vsoch-caliper@users.noreply.github.com",
                "timestamp": "2021-01-17T14:07:01-0700"
            },
            {
                "insertions": 1,
                "deletions": 0,
                "lines": 1,
                "object": "/tmp/sif-uqcnahpz/sif/main/__init__.py",
                "commit": "99fd2482cf88dfcfd157ff9fc4f1db79605e4189",
                "author": "vsoch-caliper@users.noreply.github.com",
                "timestamp": "2021-01-17T14:07:01-0700"
            },
            {
                "insertions": 101,
                "deletions": 0,
                "lines": 101,
                "object": "/tmp/sif-uqcnahpz/sif/main/extra.py",
                "commit": "99fd2482cf88dfcfd157ff9fc4f1db79605e4189",
                "author": "vsoch-caliper@users.noreply.github.com",
                "timestamp": "2021-01-17T14:07:01-0700"
            },
            {
                "insertions": 412,
                "deletions": 0,
                "lines": 412,
                "object": "/tmp/sif-uqcnahpz/sif/main/header.py",
                "commit": "99fd2482cf88dfcfd157ff9fc4f1db79605e4189",
                "author": "vsoch-caliper@users.noreply.github.com",
                "timestamp": "2021-01-17T14:07:01-0700"
            },
            {
                "insertions": 18,
                "deletions": 0,
                "lines": 18,
                "object": "/tmp/sif-uqcnahpz/sif/utils/__init__.py",
                "commit": "99fd2482cf88dfcfd157ff9fc4f1db79605e4189",
                "author": "vsoch-caliper@users.noreply.github.com",
                "timestamp": "2021-01-17T14:07:01-0700"
            },
            {
                "insertions": 109,
                "deletions": 0,
                "lines": 109,
                "object": "/tmp/sif-uqcnahpz/sif/utils/cache.py",
                "commit": "99fd2482cf88dfcfd157ff9fc4f1db79605e4189",
                "author": "vsoch-caliper@users.noreply.github.com",
                "timestamp": "2021-01-17T14:07:01-0700"
            },
            {
                "insertions": 210,
                "deletions": 0,
                "lines": 210,
                "object": "/tmp/sif-uqcnahpz/sif/utils/fileio.py",
                "commit": "99fd2482cf88dfcfd157ff9fc4f1db79605e4189",
                "author": "vsoch-caliper@users.noreply.github.com",
                "timestamp": "2021-01-17T14:07:01-0700"
            },
            {
                "insertions": 180,
                "deletions": 0,
                "lines": 180,
                "object": "/tmp/sif-uqcnahpz/sif/utils/names.py",
                "commit": "99fd2482cf88dfcfd157ff9fc4f1db79605e4189",
                "author": "vsoch-caliper@users.noreply.github.com",
                "timestamp": "2021-01-17T14:07:01-0700"
            },
            {
                "insertions": 141,
                "deletions": 0,
                "lines": 141,
                "object": "/tmp/sif-uqcnahpz/sif/utils/terminal.py",
                "commit": "99fd2482cf88dfcfd157ff9fc4f1db79605e4189",
                "author": "vsoch-caliper@users.noreply.github.com",
                "timestamp": "2021-01-17T14:07:01-0700"
            },
            {
                "insertions": 2,
                "deletions": 2,
                "lines": 4,
                "object": "/tmp/sif-uqcnahpz/sif/version.py",
                "commit": "99fd2482cf88dfcfd157ff9fc4f1db79605e4189",
                "author": "vsoch-caliper@users.noreply.github.com",
                "timestamp": "2021-01-17T14:07:01-0700"
            }
        ],
        "by-group": {
            "insertions": 2879,
            "deletions": 18,
            "lines": 2897
        }
    }
}